fastapi_deferred_init-0.2.9.dist-info/METADATA
fastapi_deferred_init-0.2.9.dist-info/WHEEL
fastapi_deferred_init-0.2.9.dist-info/entry_points.txt
fastapi_deferred_init-0.2.9.dist-info/licenses/LICENSE
fastapi_deferred_init/__init__.py
fastapi_deferred_init/py.typed
fastapi_deferred_init/routing.py
fastapi_deferred_init-0.2.9.dist-info/RECORD
