Metadata-Version: 2.1
Name: fastapi-deferred-init
Version: 0.2.9
Summary: Faster FastAPI start-up time for Projects with many nested routers
Keywords: fastapi,speed,router
Author-Email: Jan Vollmer <jan@vllmr.dev>
License: MIT
Classifier: Framework :: FastAPI
Project-URL: Source, https://github.com/jvllmr/fastapi-deferred-init
Requires-Python: >=3.9
Requires-Dist: fastapi>=0.120.4
